[{"__type__":"cc.Prefab","_name":"ColorPanelV2","data":{"__id__":1}},{"__type__":"cc.Node","_name":"ColorPanelV2","_children":[{"__id__":2}],"_components":[{"__id__":4}],"_prefab":{"__type__":"cc.PrefabInfo","root":{"__id__":1},"asset":{"__uuid__":"daHzKV0BdKuK7CctcSkYuO"},"fileId":"a3UG4LA4xJg4sQMhEdtX6t"},"_contentSize":{"__type__":"cc.Size","width":174,"height":512},"_trs":{"__type__":"TypedArray","ctor":"Float64Array","array":[0,0,0,0,0,0,1,1,1,1]}},{"__type__":"cc.Node","_name":"paintNode","_parent":{"__id__":1},"_children":[{"__id__":3}],"_components":[{"__type__":"cc.Mask","node":{"__id__":2},"_materials":[{"__uuid__":"ecpdLyjvZBwrvm+cedCcQy"}]},{"__type__":"cc.Widget","node":{"__id__":2},"_alignFlags":45,"_originalWidth":589,"_originalHeight":486}],"_prefab":{"__type__":"cc.PrefabInfo","root":{"__id__":1},"asset":{"__uuid__":"daHzKV0BdKuK7CctcSkYuO"},"fileId":"88Ig6eJOJEDLdJsgnR62qw"},"_contentSize":{"__type__":"cc.Size","width":174,"height":512},"_trs":{"__type__":"TypedArray","ctor":"Float64Array","array":[0,0,0,0,0,0,1,1,1,1]},"_groupIndex":2,"groupIndex":2},{"__type__":"cc.Node","_name":"ColorPanelV2","_parent":{"__id__":2},"_components":[{"__type__":"cc.Sprite","node":{"__id__":3},"_materials":[{"__uuid__":"ecpdLyjvZBwrvm+cedCcQy"}],"_spriteFrame":{"__uuid__":"b3nhis6FtAy5siV5x9DYvn"},"_sizeMode":0},{"__type__":"38f4exKynpMn7aOU8mHX/za","node":{"__id__":3},"camera":{"__id__":4},"renderNode":{"__id__":2}},{"__type__":"cc.Widget","node":{"__id__":3},"_alignFlags":45,"_originalWidth":174,"_originalHeight":512}],"_prefab":{"__type__":"cc.PrefabInfo","root":{"__id__":1},"asset":{"__uuid__":"daHzKV0BdKuK7CctcSkYuO"},"fileId":"7aFFBedAVPbLl2sBXTc+QK"},"_contentSize":{"__type__":"cc.Size","width":174,"height":512},"_anchorPoint":{"__type__":"cc.Vec2"},"_trs":{"__type__":"TypedArray","ctor":"Float64Array","array":[-87,-256,0,0,0,0,1,1,1,1]},"_groupIndex":2,"groupIndex":2},{"__type__":"cc.Camera","node":{"__id__":1},"_cullingMask":-12,"_zoomRatio":1.5,"_orthoSize":1,"_nearClip":0.1}]